lap_random_spanish/__init__.py
lap_random_spanish/functions.py
lap_random_spanish-1.6.dist-info/METADATA
lap_random_spanish-1.6.dist-info/WHEEL
lap_random_spanish-1.6.dist-info/top_level.txt
lap_random_spanish-1.6.dist-info/RECORD
