Metadata-Version: 2.1
Name: lap-random-spanish
Version: 1.6
Summary: Library to obtain names of Spanish men and women as well as surnames
Home-page: https://github.com/LuisAlbertoPerezDeLaCruz/lap_random_spanish.git
Author: @lap.com
Author-email: lapfreelance56@gmail.com
License: GNU GPL
Platform: UNKNOWN
Requires-Dist: pandas
